{
  "Workflows": [
    {
      "Path": null,
      "SortBy": 0,
      "VariablesSectionElementsOrder": [],
      "ArgumentsSectionElementsOrder": null,
      "ConstantsSectionElementsOrder": [],
      "AddedNamespaces": null
    },
    {
      "Path": "Main.xaml",
      "SortBy": 0,
      "VariablesSectionElementsOrder": [
        "logTable&Sequence_1",
        "outoffdt&Sequence_1",
        "dt_table&Sequence_1",
        "DictName&Sequence_1"
      ],
      "ArgumentsSectionElementsOrder": [],
      "ConstantsSectionElementsOrder": [],
      "AddedNamespaces": null
    }
  ]
}